Metadata-Version: 2.1
Name: models-for-plutus
Version: 0.1.0
Summary: models for plutus app
Classifier: Programming Language :: Python :: 3.11
Classifier: License :: OSI Approved :: MIT License
Classifier: Operating System :: OS Independent
Requires-Python: >=3.6
